odoo10_addon_sale_promotion_rule_delivery-10.0.1.0.0.99.dev7-py3.8-nspkg.pth
odoo/addons/sale_promotion_rule_delivery/README.rst
odoo/addons/sale_promotion_rule_delivery/__init__.py
odoo/addons/sale_promotion_rule_delivery/__manifest__.py
odoo/addons/sale_promotion_rule_delivery/i18n/ca.po
odoo/addons/sale_promotion_rule_delivery/i18n/es.po
odoo/addons/sale_promotion_rule_delivery/i18n/sale_promotion_rule_delivery.pot
odoo/addons/sale_promotion_rule_delivery/models/__init__.py
odoo/addons/sale_promotion_rule_delivery/models/sale_promotion_rule.py
odoo/addons/sale_promotion_rule_delivery/readme/CONTRIBUTORS.rst
odoo/addons/sale_promotion_rule_delivery/readme/DESCRIPTION.rst
odoo/addons/sale_promotion_rule_delivery/readme/ROADMAP.rst
odoo/addons/sale_promotion_rule_delivery/static/description/icon.png
odoo/addons/sale_promotion_rule_delivery/static/description/index.html
odoo/addons/sale_promotion_rule_delivery/tests/__init__.py
odoo/addons/sale_promotion_rule_delivery/tests/test_promotion.py
odoo10_addon_sale_promotion_rule_delivery-10.0.1.0.0.99.dev7.dist-info/METADATA
odoo10_addon_sale_promotion_rule_delivery-10.0.1.0.0.99.dev7.dist-info/WHEEL
odoo10_addon_sale_promotion_rule_delivery-10.0.1.0.0.99.dev7.dist-info/namespace_packages.txt
odoo10_addon_sale_promotion_rule_delivery-10.0.1.0.0.99.dev7.dist-info/top_level.txt
odoo10_addon_sale_promotion_rule_delivery-10.0.1.0.0.99.dev7.dist-info/RECORD
